nestedlisttoflat/__init__.py
nestedlisttoflat/nestedlisttoflat.py
nestedlisttoflat-2.1.2.dist-info/LICENSE.txt
nestedlisttoflat-2.1.2.dist-info/METADATA
nestedlisttoflat-2.1.2.dist-info/WHEEL
nestedlisttoflat-2.1.2.dist-info/top_level.txt
nestedlisttoflat-2.1.2.dist-info/RECORD
